PaperDown/HTMLparsers.py
PaperDown/NetInfo.py
PaperDown/__init__.py
PaperDown/run.py
PaperDown-0.1.dist-info/METADATA
PaperDown-0.1.dist-info/WHEEL
PaperDown-0.1.dist-info/top_level.txt
PaperDown-0.1.dist-info/RECORD
